easy_terminal/__init__.py
easy_terminal/terminal.py
easy_terminal-0.8.1.dist-info/LICENSE
easy_terminal-0.8.1.dist-info/METADATA
easy_terminal-0.8.1.dist-info/WHEEL
easy_terminal-0.8.1.dist-info/top_level.txt
easy_terminal-0.8.1.dist-info/RECORD
