Metadata-Version: 2.1
Name: easy-terminal
Version: 0.8.1
Summary: A tool that help using python function into terminal
Home-page: https://github.com/ThePhoenix78/easy-terminal
Download-URL: https://github.com/ThePhoenix78/easy-terminal/tarball/master
Author: ThePhoenix78
Author-email: thephoenix788@gmail.com
License: MIT
Keywords: wrapper,event,terminal,cmd
Classifier: Programming Language :: Python :: 3
Classifier: License :: OSI Approved :: MIT License
Classifier: Operating System :: OS Independent
License-File: LICENSE
Requires-Dist: easy-events (>=2.11.3)
